aimengine/__init__.py
aimengine-0.0.1.dist-info/LICENSE
aimengine-0.0.1.dist-info/METADATA
aimengine-0.0.1.dist-info/WHEEL
aimengine-0.0.1.dist-info/top_level.txt
aimengine-0.0.1.dist-info/RECORD
