Metadata-Version: 2.1
Name: aimengine
Version: 0.0.1
Summary: Aim Assistance
Home-page: https://aimengine.com
Author: AimEngine
Author-email: support@aimengine.com
Project-URL: Bug Tracker, https://aimengine.com
Classifier: Programming Language :: Python :: 3
Classifier: License :: OSI Approved :: MIT License
Classifier: Operating System :: OS Independent
Requires-Python: >=3.10
License-File: LICENSE
Requires-Dist: ultralytics
